var samknob = {
"type": "FeatureCollection",
"crs": { "type": "name", "properties": { "name": "urn:ogc:def:crs:OGC:1.3:CRS84" } },
"features": [
{ "type": "Feature", "properties": { "id": 1, "descrip": "unc well" }, "geometry": { "type": "Point", "coordinates": [-82.895528, 35.329676 ] } }
]
}
